mathsys/__init__.py
mathsys/__main__.py
mathsys/__pycache__/__init__.cpython-311.pyc
mathsys/__pycache__/__main__.cpython-311.pyc
mathsys/dev/__init__.py
mathsys/dev/py.typed
mathsys/dev/__pycache__/__init__.cpython-311.pyc
mathsys/dev/bin/main.rs
mathsys/dev/bin/context/_infinity.rs
mathsys/dev/bin/context/_nexists.rs
mathsys/dev/bin/context/_number.rs
mathsys/dev/bin/context/_undefined.rs
mathsys/dev/bin/context/_variable.rs
mathsys/dev/bin/data/comment.rs
mathsys/dev/bin/data/declaration.rs
mathsys/dev/bin/data/definition.rs
mathsys/dev/bin/data/equation.rs
mathsys/dev/bin/data/expression.rs
mathsys/dev/bin/data/factor.rs
mathsys/dev/bin/data/infinite.rs
mathsys/dev/bin/data/limit.rs
mathsys/dev/bin/data/nest.rs
mathsys/dev/bin/data/node.rs
mathsys/dev/bin/data/number.rs
mathsys/dev/bin/data/start.rs
mathsys/dev/bin/data/term.rs
mathsys/dev/bin/data/variable.rs
mathsys/dev/bin/data/vector.rs
mathsys/dev/bin/lib/allocator.rs
mathsys/dev/bin/lib/converter.rs
mathsys/dev/bin/lib/formatting.rs
mathsys/dev/bin/lib/runtime.rs
mathsys/dev/bin/lib/rustc.rs
mathsys/dev/bin/lib/stack.rs
mathsys/dev/bin/lib/stdout.rs
mathsys/dev/main/builder.py
mathsys/dev/main/ir.py
mathsys/dev/main/latex.py
mathsys/dev/main/parser.py
mathsys/dev/main/syntax.py
mathsys/dev/main/__pycache__/__init__.cpython-311.pyc
mathsys/dev/main/__pycache__/__init__.cpython-313.pyc
mathsys/dev/main/__pycache__/builder.cpython-311.pyc
mathsys/dev/main/__pycache__/generator.cpython-311.pyc
mathsys/dev/main/__pycache__/ir.cpython-311.pyc
mathsys/dev/main/__pycache__/ir.cpython-313.pyc
mathsys/dev/main/__pycache__/latex.cpython-311.pyc
mathsys/dev/main/__pycache__/parser.cpython-311.pyc
mathsys/dev/main/__pycache__/parser.cpython-313.pyc
mathsys/dev/main/__pycache__/syntax.cpython-311.pyc
mathsys/dev/main/__pycache__/syntax.cpython-313.pyc
mathsys/dev/main/__pycache__/tokenizer.cpython-313.pyc
mathsys/dev/source/all.o
mathsys/dev/source/unix-x86-64.o
mathsys/dev/source/unix-x86-64.sh
mathsys-3.9.16.dist-info/METADATA
mathsys-3.9.16.dist-info/WHEEL
mathsys-3.9.16.dist-info/top_level.txt
mathsys-3.9.16.dist-info/RECORD
