Metadata-Version: 2.4
Name: mathsys
Version: 3.9.16
Summary: The Domain Specific Language for math.
Author-email: Alejandro Vaz <support@abscissa.eu>
License: SEE LICENSE IN https://docs.abscissa.eu
Keywords: dsl,math,mathsys,compiler,language
Classifier: Development Status :: 5 - Production/Stable
Classifier: Programming Language :: Python :: 3
Classifier: Operating System :: OS Independent
Requires-Python: >=3.11
Requires-Dist: lark
